social_auth_presspass/__init__.py
social_auth_presspass/backends.py
social_auth_presspass/pipelines.py
src/__init__.py
src/backends.py
src/pipelines.py
social_auth_presspass-0.2.0.dist-info/LICENSE
social_auth_presspass-0.2.0.dist-info/METADATA
social_auth_presspass-0.2.0.dist-info/WHEEL
social_auth_presspass-0.2.0.dist-info/top_level.txt
social_auth_presspass-0.2.0.dist-info/RECORD
